setup.py
CalculatorSuraj/Addition.py
CalculatorSuraj/Division.py
CalculatorSuraj/Multiplication.py
CalculatorSuraj/Subtraction.py
CalculatorSuraj/__init__.py
CalculatorSuraj.egg-info/PKG-INFO
CalculatorSuraj.egg-info/SOURCES.txt
CalculatorSuraj.egg-info/dependency_links.txt
CalculatorSuraj.egg-info/top_level.txt