Metadata-Version: 1.1
Name: CalculatorSuraj
Version: 1.1.0
Summary: My first Python package ... Calculator
Home-page: UNKNOWN
Author: suraj_songara
Author-email: suraj_songara@persistent.com
License: UNKNOWN
Keywords: python,first package
Platform: UNKNOWN
Classifier: Development Status :: 3 - Alpha
Classifier: Intended Audience :: Education
Classifier: Programming Language :: Python :: 2
Classifier: Programming Language :: Python :: 3
Classifier: Operating System :: MacOS :: MacOS X
Classifier: Operating System :: Microsoft :: Windows
